pypowerbi/__init__.py
pypowerbi/client.py
pypowerbi/dataset.py
pypowerbi/datasets.py
pypowerbi/features.py
pypowerbi/group.py
pypowerbi/groups.py
pypowerbi/import_class.py
pypowerbi/imports.py
pypowerbi/report.py
pypowerbi/reports.py
pypowerbi/utils.py
pypowerbi_latest-0.231.dist-info/DESCRIPTION.rst
pypowerbi_latest-0.231.dist-info/METADATA
pypowerbi_latest-0.231.dist-info/RECORD
pypowerbi_latest-0.231.dist-info/WHEEL
pypowerbi_latest-0.231.dist-info/metadata.json
pypowerbi_latest-0.231.dist-info/top_level.txt
